pastawrap/__init__.py
pastawrap/pastawrap.py
pastawrap/utility.py
pastawrap-0.1.0.dist-info/LICENSE
pastawrap-0.1.0.dist-info/METADATA
pastawrap-0.1.0.dist-info/WHEEL
pastawrap-0.1.0.dist-info/top_level.txt
pastawrap-0.1.0.dist-info/RECORD
