Metadata-Version: 2.1
Name: pastawrap
Version: 0.1.0
Summary: The Python wrapper for ratPASTA - R-based Awesome Toolkit for PASTA.
Home-page: https://github.com/davorvr/pastawrap
Author: Davor Virag, Ivan Kodvanj, Jan Homolak
Author-email: davor.virag@gmail.com
Maintainer: Davor Virag
Maintainer-email: davor.virag@gmail.com
License: UNKNOWN
Platform: UNKNOWN
Classifier: Programming Language :: Python :: 3
Classifier: Programming Language :: R
Classifier: License :: OSI Approved :: GNU General Public License v3 (GPLv3)
Classifier: Operating System :: OS Independent
Classifier: Intended Audience :: Science/Research
Classifier: Topic :: Scientific/Engineering
Requires-Python: >=3.8
Requires-Dist: rpy2 (>=3.3.0)
Requires-Dist: pandas (>=1.0.0)
